tests/__init__.py
tests/test_timer.py
thyming/__init__.py
thyming/timer.py
thyming-0.1.0.dist-info/LICENSE
thyming-0.1.0.dist-info/METADATA
thyming-0.1.0.dist-info/WHEEL
thyming-0.1.0.dist-info/top_level.txt
thyming-0.1.0.dist-info/RECORD
