Metadata-Version: 2.1
Name: thyming
Version: 0.1.0
Summary: Custom timer
Author-email: MatthewBaggins <bagginsmatthew@gmail.com>
License: MIT License
Project-URL: Homepage, https://github.com/MatthewBaggins/thyming
Keywords: timer,timing
Classifier: License :: OSI Approved :: MIT License
Classifier: Programming Language :: Python
Classifier: Programming Language :: Python :: 3
Classifier: Operating System :: OS Independent
Requires-Python: >=3.8
License-File: LICENSE
Requires-Dist: typing-extensions
Provides-Extra: dev
Requires-Dist: black ; extra == 'dev'
Requires-Dist: pylint ; extra == 'dev'
Requires-Dist: pip-tools ; extra == 'dev'
Requires-Dist: pytest ; extra == 'dev'
